{
  "date": "2026/02/09",
  "ymd": "20260209",
  "generated_at": "2026-02-09 00:00:00",
  "total_races": 5,
  "hit_count": 0,
  "miss_count": 5,
  "unavailable_count": 0,
  "total_investment": 12000,
  "total_return": 0,
  "total_profit": -12000,
  "hit_rate": 0.0,
  "recovery_rate": 0.0,
  "races": [
    {
      "race_id": "202605010412",
      "venue": "東京",
      "race_num": "12",
      "race_name": "4歳以上1勝クラス",
      "distance": 1300,
      "track": "ダ",
      "status": "不的中",
      "predicted": [
        "15-3-9"
      ],
      "actual": [
        "15-6-7"
      ],
      "result_sanrenpuku": "15-6-7",
      "payout_sanrenpuku": 6715,
      "hit": false,
      "investment": 1200,
      "return": 0,
      "profit": -1200,
      "payouts": {
        "単勝": 790,
        "複勝": 7156,
        "枠連": 1810,
        "馬連": 715,
        "ワイド": 71567615,
        "馬単": 715,
        "三連複": 6715,
        "三連単": 7156
      },
      "horse_weights": [
        {
          "rank": 1,
          "horse_number": "7",
          "weight": "452(+16)"
        },
        {
          "rank": 2,
          "horse_number": "15",
          "weight": "520(+12)"
        },
        {
          "rank": 3,
          "horse_number": "6",
          "weight": "540(0)"
        }
      ],
      "weather": "曇",
      "track_condition": "稍"
    },
    {
      "race_id": "202608020412",
      "venue": "京都",
      "race_num": "12",
      "race_name": "4歳以上2勝クラス",
      "distance": 1200,
      "track": "ダ",
      "status": "不的中",
      "predicted": [
        "2-4-9"
      ],
      "actual": [
        "13-14-15"
      ],
      "result_sanrenpuku": "13-14-15",
      "payout_sanrenpuku": 131415,
      "hit": false,
      "investment": 1200,
      "return": 0,
      "profit": -1200,
      "payouts": {
        "単勝": 3360,
        "複勝": 141513,
        "枠連": 860,
        "馬連": 1415,
        "ワイド": 141513141315,
        "馬単": 1415,
        "三連複": 131415,
        "三連単": 141513
      },
      "horse_weights": [
        {
          "rank": 1,
          "horse_number": "14",
          "weight": "468(+2)"
        },
        {
          "rank": 2,
          "horse_number": "15",
          "weight": "478(+4)"
        },
        {
          "rank": 3,
          "horse_number": "13",
          "weight": "528(+2)"
        }
      ],
      "weather": "曇",
      "track_condition": "良"
    },
    {
      "race_id": "202610010609",
      "venue": "小倉",
      "race_num": "09",
      "race_name": "かささぎ賞",
      "distance": 1200,
      "track": "芝",
      "status": "不的中",
      "predicted": [
        "5-7-9"
      ],
      "actual": [
        "10-15-4"
      ],
      "result_sanrenpuku": "10-15-4",
      "payout_sanrenpuku": 41015,
      "hit": false,
      "investment": 1200,
      "return": 0,
      "profit": -1200,
      "payouts": {
        "単勝": 2180,
        "複勝": 15410,
        "枠連": 2200,
        "馬連": 415,
        "ワイド": 4151015410,
        "馬単": 154,
        "三連複": 41015,
        "三連単": 15410
      },
      "horse_weights": [
        {
          "rank": 1,
          "horse_number": "15",
          "weight": "448(+2)"
        },
        {
          "rank": 2,
          "horse_number": "4",
          "weight": "474(-6)"
        },
        {
          "rank": 3,
          "horse_number": "10",
          "weight": "444(0)"
        }
      ],
      "weather": "曇",
      "track_condition": "良"
    },
    {
      "race_id": "202610010603",
      "venue": "小倉",
      "race_num": "03",
      "race_name": "4歳以上1勝クラス",
      "distance": 1000,
      "track": "ダ",
      "status": "不的中",
      "predicted": [
        "4-8-9"
      ],
      "actual": [
        "11-4-6"
      ],
      "result_sanrenpuku": "11-4-6",
      "payout_sanrenpuku": 4611,
      "hit": false,
      "investment": 1200,
      "return": 0,
      "profit": -1200,
      "payouts": {
        "単勝": 790,
        "複勝": 1164,
        "枠連": 1260,
        "馬連": 611,
        "ワイド": 61141146,
        "馬単": 116,
        "三連複": 4611,
        "三連単": 1164
      },
      "horse_weights": [
        {
          "rank": 1,
          "horse_number": "11",
          "weight": "452(0)"
        },
        {
          "rank": 2,
          "horse_number": "6",
          "weight": "496(-2)"
        },
        {
          "rank": 3,
          "horse_number": "4",
          "weight": "484(-6)"
        }
      ],
      "weather": "曇",
      "track_condition": "良"
    },
    {
      "race_id": "202610010602",
      "venue": "小倉",
      "race_num": "02",
      "race_name": "3歳未勝利",
      "distance": 1200,
      "track": "芝",
      "status": "不的中",
      "predicted": [
        "10-2-3"
      ],
      "actual": [
        "1-10-4"
      ],
      "result_sanrenpuku": "1-10-4",
      "payout_sanrenpuku": 1410,
      "hit": false,
      "investment": 7200,
      "return": 0,
      "profit": -7200,
      "payouts": {
        "単勝": 280,
        "複勝": 1410,
        "枠連": 1990,
        "馬連": 1930,
        "ワイド": 14110410,
        "馬単": 2630,
        "三連複": 1410,
        "三連単": 1410
      },
      "horse_weights": [
        {
          "rank": 1,
          "horse_number": "1",
          "weight": "470(+2)"
        },
        {
          "rank": 2,
          "horse_number": "4",
          "weight": "420(+2)"
        },
        {
          "rank": 3,
          "horse_number": "10",
          "weight": "428(0)"
        }
      ],
      "weather": "曇",
      "track_condition": "良"
    }
  ]
}