{
  "date": "2026/03/12",
  "ymd": "20260312",
  "generated_at": "2026-03-12 13:54:15",
  "total_races": 4,
  "hit_count": 1,
  "miss_count": 3,
  "unavailable_count": 0,
  "no_pred_count": 0,
  "valid_races": 4,
  "total_investment": 11200,
  "total_return": 1060,
  "total_profit": -10140,
  "hit_rate": 25.0,
  "recovery_rate": 9.5,
  "races": [
    {
      "race_id": "202644031211",
      "venue": "大井",
      "race_num": "11",
      "race_name": "出羽坂賞競走(B3)",
      "distance": 2000,
      "track": "ダ",
      "start_time": "16:55",
      "betting_plan": {
        "軸": [
          {
            "馬番": 5,
            "馬名": "ペイシャコパ",
            "人気": 3,
            "評価": "◎",
            "スコア": 89.0,
            "補正後スコア": 89.0,
            "内訳": {
              "馬体重増減": 80,
              "当日人気": 70,
              "経験値": 100,
              "騎手厩舎": 100,
              "距離馬場適性": 100,
              "脚質": 100
            },
            "根拠": "前走3-5位人気、体重減で好調、実績豊富、好騎手、適性抜群、展開有利、軸馬候補",
            "断層役割": "軸馬候補",
            "危険フラグ": false,
            "危険理由": []
          },
          {
            "馬番": 1,
            "馬名": "ヨシイチ",
            "人気": 1,
            "評価": "○",
            "スコア": 84.65,
            "補正後スコア": 84.65,
            "内訳": {
              "馬体重増減": 40,
              "当日人気": 100,
              "経験値": 100,
              "騎手厩舎": 75,
              "距離馬場適性": 92,
              "脚質": 85
            },
            "根拠": "前走1-2位人気、実績豊富、適性抜群、軸馬候補",
            "断層役割": "軸馬候補",
            "危険フラグ": false,
            "危険理由": []
          }
        ],
        "対抗": [
          {
            "馬番": 11,
            "馬名": "ヴュルディヒ",
            "人気": 2,
            "評価": "▲",
            "スコア": 49.0,
            "補正後スコア": 49.0,
            "根拠": "前走1-2位人気、実績豊富、軸馬候補",
            "断層役割": "軸馬候補",
            "斤量騎手ボーナス": 2,
            "斤量騎手詳細": {
              "斤量差": 0.0,
              "騎手替わり": "+2(騎手乗り替わり: 吉原寛人→和田譲治)"
            }
          },
          {
            "馬番": 8,
            "馬名": "エスプリブルズアイ",
            "人気": 4,
            "評価": "▲",
            "スコア": 76.5,
            "補正後スコア": 76.5,
            "根拠": "前走3-5位人気、体重減で好調、実績豊富、適性抜群、展開有利、軸馬候補",
            "断層役割": "軸馬候補",
            "斤量騎手ボーナス": -5,
            "斤量騎手詳細": {
              "斤量差": 2.0,
              "斤量ボーナス": "-10(大幅増量)",
              "騎手替わり": "+5(穴馬騎手乗り替わり: 西啓太→鷹見陸)"
            }
          }
        ],
        "穴": [
          {
            "馬番": 2,
            "馬名": "ジーゲル",
            "人気": 12,
            "評価": "△",
            "スコア": 31.0,
            "補正後スコア": 31.0,
            "根拠": "実績豊富、穴馬候補",
            "断層役割": "穴馬候補",
            "斤量騎手ボーナス": 0,
            "斤量騎手詳細": {
              "斤量差": 0.0
            }
          }
        ],
        "相手": [
          {
            "馬番": 11,
            "馬名": "ヴュルディヒ",
            "評価": "△",
            "スコア": 49.0,
            "根拠": "前走1-2位人気、実績豊富、軸馬候補"
          },
          {
            "馬番": 8,
            "馬名": "エスプリブルズアイ",
            "評価": "△",
            "スコア": 76.5,
            "根拠": "前走3-5位人気、体重減で好調、実績豊富、適性抜群、展開有利、軸馬候補"
          },
          {
            "馬番": 2,
            "馬名": "ジーゲル",
            "評価": "△",
            "スコア": 31.0,
            "根拠": "実績豊富、穴馬候補"
          }
        ],
        "買い目タイプ": "三連複フォーメーション(断層役割ベース・精度改善v3)",
        "組み合わせ数": 9,
        "合成オッズ": 3.5,
        "合成オッズ_全体": 1.2,
        "合成オッズ_方法": "actual",
        "賭け金調整": "コア合成オッズ3.5倍(基本100円/点)",
        "全買い目": [
          "1-5-8",
          "1-2-5",
          "5-8-11",
          "2-5-11",
          "2-5-8",
          "1-8-11",
          "1-2-11",
          "1-2-8",
          "2-8-11"
        ],
        "穴ボックス発動": false,
        "穴ボックス_upset_score": 0,
        "穴ボックス_upset_理由": [],
        "穴ボックス_買い目": [],
        "穴ボックス_追加点数": 0,
        "相手ボックス_買い目": [
          "2-8-11"
        ],
        "相手ボックス_追加点数": 1,
        "ワイド候補": [
          {
            "軸": {
              "馬番": 1,
              "馬名": "ヨシイチ",
              "スコア": 84.65,
              "役割": "軸馬候補"
            },
            "穴": {
              "馬番": 2,
              "馬名": "ジーゲル",
              "スコア": 31.0,
              "役割": "穴馬候補"
            },
            "ワイドオッズ": null,
            "買い目": "1-2",
            "投資": 500
          },
          {
            "軸": {
              "馬番": 11,
              "馬名": "ヴュルディヒ",
              "スコア": 49.0,
              "役割": "軸馬候補"
            },
            "穴": {
              "馬番": 2,
              "馬名": "ジーゲル",
              "スコア": 31.0,
              "役割": "穴馬候補"
            },
            "ワイドオッズ": null,
            "買い目": "11-2",
            "投資": 500
          }
        ],
        "複勝候補": [],
        "旧ロジック": {
          "旧_軸頭数": 3,
          "旧_相手頭数": 4,
          "旧_組み合わせ数": 31,
          "旧_投資額": 3100,
          "旧_買い目タイプ": "三連複フォーメーション(スコア順)"
        }
      },
      "status": "不的中",
      "predicted": [
        "1-5-8",
        "1-2-5",
        "5-8-11",
        "2-5-11",
        "2-5-8",
        "1-8-11",
        "1-2-11",
        "1-2-8",
        "2-8-11"
      ],
      "actual": [
        "9-11-3"
      ],
      "result_sanrenpuku": "9-11-3",
      "payout_sanrenpuku": 14500,
      "hit": false,
      "payout_missing": false,
      "investment": 900,
      "return": 0,
      "profit": -900,
      "payouts": {
        "単勝": 1500,
        "複勝": 210,
        "枠連": 1320,
        "馬連": 1980,
        "ワイド": 770,
        "枠単": 2980,
        "馬単": 5320,
        "三連複": 14500,
        "三連単": 74130
      },
      "horse_weights": [
        {
          "rank": 1,
          "horse_number": "9",
          "weight": "477(-5)"
        },
        {
          "rank": 2,
          "horse_number": "11",
          "weight": "488(+2)"
        },
        {
          "rank": 3,
          "horse_number": "3",
          "weight": "480(+6)"
        }
      ],
      "all_horses_result": [
        {
          "馬番": "9",
          "着順": 1,
          "人気": 6,
          "馬名": "ドウジギリ",
          "馬体重": "477(-5)",
          "DASスコア": null,
          "役割": "予測外"
        },
        {
          "馬番": "11",
          "着順": 2,
          "人気": 2,
          "馬名": "ヴュルディヒ",
          "馬体重": "488(+2)",
          "DASスコア": 49.0,
          "役割": "相手"
        },
        {
          "馬番": "3",
          "着順": 3,
          "人気": 8,
          "馬名": "リックマーベル",
          "馬体重": "480(+6)",
          "DASスコア": null,
          "役割": "予測外"
        },
        {
          "馬番": "7",
          "着順": 4,
          "人気": 9,
          "馬名": "ゲールタクト",
          "馬体重": "461(+3)",
          "DASスコア": null,
          "役割": "予測外"
        },
        {
          "馬番": "4",
          "着順": 5,
          "人気": 4,
          "馬名": "マイネルオデーサ",
          "馬体重": "445(+1)",
          "DASスコア": null,
          "役割": "予測外"
        },
        {
          "馬番": "6",
          "着順": 6,
          "人気": 11,
          "馬名": "レペンテ",
          "馬体重": "409(0)",
          "DASスコア": null,
          "役割": "予測外"
        },
        {
          "馬番": "12",
          "着順": 7,
          "人気": 10,
          "馬名": "グッドボーイ",
          "馬体重": "464(-3)",
          "DASスコア": null,
          "役割": "予測外"
        },
        {
          "馬番": "2",
          "着順": 8,
          "人気": 12,
          "馬名": "ジーゲル",
          "馬体重": "401(0)",
          "DASスコア": 31.0,
          "役割": "相手"
        },
        {
          "馬番": "5",
          "着順": 9,
          "人気": 5,
          "馬名": "ペイシャコパ",
          "馬体重": "486(+4)",
          "DASスコア": 89.0,
          "役割": "軸"
        },
        {
          "馬番": "8",
          "着順": 10,
          "人気": 3,
          "馬名": "エスプリブルズアイ",
          "馬体重": "474(+2)",
          "DASスコア": 76.5,
          "役割": "相手"
        },
        {
          "馬番": "1",
          "着順": 11,
          "人気": 1,
          "馬名": "ヨシイチ",
          "馬体重": "500(-3)",
          "DASスコア": 84.65,
          "役割": "軸"
        },
        {
          "馬番": "10",
          "着順": 12,
          "人気": 7,
          "馬名": "リュミエール",
          "馬体重": "473(-4)",
          "DASスコア": null,
          "役割": "予測外"
        }
      ],
      "race_verification": {
        "axis_best_rank": 9,
        "axis_in_top3": false,
        "93rule_pop_in_top3_count": 1,
        "93rule_pop_in_top3_rate": 33.3,
        "score_top1_rank": 9,
        "score_top2_rank": 11,
        "score_top1_in_top3": false,
        "predicted_in_top3_count": 1,
        "unpredicted_in_top3_count": 2,
        "miss_pattern": "軸外れ",
        "winner_popularity": 6,
        "is_upset": true,
        "predicted_synthetic_odds": 3.5,
        "actual_payout": 14500,
        "odds_ratio": 41.429,
        "opponent_in_top3_count": 1
      },
      "virtual_bets_result": {
        "複勝_軸1": {
          "type": "複勝",
          "投資": 300,
          "払戻": 0,
          "収支": -300,
          "的中": false
        },
        "複勝_軸2": {
          "type": "複勝",
          "投資": 300,
          "払戻": 0,
          "収支": -300,
          "的中": false
        },
        "ワイド_軸1-2": {
          "type": "ワイド",
          "投資": 500,
          "払戻": 0,
          "収支": -500,
          "的中": false
        },
        "馬連_軸1-2": {
          "type": "馬連",
          "投資": 500,
          "払戻": 0,
          "収支": -500,
          "的中": false
        }
      },
      "weather": "晴",
      "track_condition": "良",
      "predicted_pace": "ハイペース"
    },
    {
      "race_id": "202643031211",
      "venue": "船橋",
      "race_num": "11",
      "race_name": "ネクストスター東日本重賞",
      "distance": 1200,
      "track": "ダ",
      "start_time": "20:05",
      "betting_plan": {
        "軸": [
          {
            "馬番": 3,
            "馬名": "バーバリオン",
            "人気": 5,
            "評価": "◎",
            "スコア": 82.0,
            "補正後スコア": 88.0,
            "内訳": {
              "馬体重増減": 20,
              "当日人気": 70,
              "経験値": 80,
              "騎手厩舎": 100,
              "距離馬場適性": 100,
              "脚質": 100
            },
            "根拠": "前走3-5位人気、体重増で不安、実績豊富、好騎手、適性抜群、展開有利、軸馬候補",
            "断層役割": "軸馬候補",
            "危険フラグ": false,
            "危険理由": []
          },
          {
            "馬番": 5,
            "馬名": "グルーヴィン",
            "人気": 2,
            "評価": "○",
            "スコア": 84.1,
            "補正後スコア": 87.1,
            "内訳": {
              "馬体重増減": 20,
              "当日人気": 90,
              "経験値": 80,
              "騎手厩舎": 100,
              "距離馬場適性": 88,
              "脚質": 85
            },
            "根拠": "前走1-2位人気、体重増で不安、実績豊富、好騎手、軸馬候補",
            "断層役割": "軸馬候補",
            "危険フラグ": false,
            "危険理由": []
          },
          {
            "馬番": 1,
            "馬名": "ベイビークエスト",
            "人気": 1,
            "評価": "○",
            "スコア": 76.1,
            "補正後スコア": 82.1,
            "内訳": {
              "馬体重増減": 20,
              "当日人気": 100,
              "経験値": 80,
              "騎手厩舎": 50,
              "距離馬場適性": 88,
              "脚質": 100
            },
            "根拠": "前走1-2位人気、体重増で不安、実績豊富、展開有利、軸馬候補",
            "断層役割": "軸馬候補",
            "危険フラグ": false,
            "危険理由": []
          }
        ],
        "対抗": [
          {
            "馬番": 6,
            "馬名": "アトレーヴフェイス",
            "人気": 3,
            "評価": "▲",
            "スコア": 63.25,
            "補正後スコア": 60.25,
            "根拠": "前走3-5位人気、実績豊富、適性抜群、軸馬候補",
            "断層役割": "軸馬候補",
            "斤量騎手ボーナス": 7,
            "斤量騎手詳細": {
              "斤量差": -1.0,
              "斤量ボーナス": "+5(減量)",
              "騎手替わり": "+2(騎手乗り替わり: 本田正重→張田昂)"
            }
          }
        ],
        "穴": [
          {
            "馬番": 8,
            "馬名": "デーレーシトロン",
            "人気": 9,
            "評価": "△",
            "スコア": 69.5,
            "補正後スコア": 75.5,
            "根拠": "体重減で好調、実績豊富、適性抜群、展開有利、穴馬候補",
            "断層役割": "穴馬候補",
            "斤量騎手ボーナス": -5,
            "斤量騎手詳細": {
              "斤量差": 1.0,
              "斤量ボーナス": "-5(増量)"
            }
          },
          {
            "馬番": 9,
            "馬名": "ノースラノビア",
            "人気": 7,
            "評価": "△",
            "スコア": 61.5,
            "補正後スコア": 58.5,
            "根拠": "体重減で好調、実績豊富、穴馬候補",
            "断層役割": "穴馬候補",
            "斤量騎手ボーナス": 5,
            "斤量騎手詳細": {
              "斤量差": 0.0,
              "騎手替わり": "+5(穴馬騎手乗り替わり: 張田昂→岡村健司)"
            }
          },
          {
            "馬番": 7,
            "馬名": "フークアンビション",
            "人気": 8,
            "評価": "△",
            "スコア": 57.25,
            "補正後スコア": 54.25,
            "根拠": "実績豊富、適性抜群、穴馬候補",
            "断層役割": "穴馬候補",
            "斤量騎手ボーナス": 10,
            "斤量騎手詳細": {
              "斤量差": -1.0,
              "斤量ボーナス": "+5(減量)",
              "騎手替わり": "+5(穴馬騎手乗り替わり: 本田正重→野畑凌)"
            }
          }
        ],
        "相手": [
          {
            "馬番": 6,
            "馬名": "アトレーヴフェイス",
            "評価": "△",
            "スコア": 63.25,
            "根拠": "前走3-5位人気、実績豊富、適性抜群、軸馬候補"
          },
          {
            "馬番": 8,
            "馬名": "デーレーシトロン",
            "評価": "△",
            "スコア": 69.5,
            "根拠": "体重減で好調、実績豊富、適性抜群、展開有利、穴馬候補"
          },
          {
            "馬番": 9,
            "馬名": "ノースラノビア",
            "評価": "△",
            "スコア": 61.5,
            "根拠": "体重減で好調、実績豊富、穴馬候補"
          },
          {
            "馬番": 7,
            "馬名": "フークアンビション",
            "評価": "△",
            "スコア": 57.25,
            "根拠": "実績豊富、適性抜群、穴馬候補"
          }
        ],
        "買い目タイプ": "三連複フォーメーション(断層役割ベース・精度改善v3)",
        "組み合わせ数": 23,
        "合成オッズ": 4.4,
        "合成オッズ_全体": 0.99,
        "合成オッズ_方法": "actual",
        "賭け金調整": "コア合成オッズ4.4倍(基本100円/点)",
        "全買い目": [
          "1-3-5",
          "3-5-6",
          "3-5-8",
          "3-5-9",
          "3-5-7",
          "1-3-6",
          "1-3-8",
          "1-3-9",
          "1-3-7",
          "3-6-8",
          "3-6-9",
          "3-6-7",
          "1-5-8",
          "1-5-9",
          "1-5-7",
          "5-6-8",
          "5-6-9",
          "5-6-7",
          "1-6-8",
          "1-6-9",
          "6-8-9",
          "6-7-8",
          "7-8-9"
        ],
        "穴ボックス発動": false,
        "穴ボックス_upset_score": 10,
        "穴ボックス_upset_理由": [
          "波乱度:中(+10)"
        ],
        "穴ボックス_買い目": [],
        "穴ボックス_追加点数": 0,
        "相手ボックス_買い目": [
          "6-8-9",
          "6-7-8",
          "7-8-9"
        ],
        "相手ボックス_追加点数": 3,
        "ワイド候補": [
          {
            "軸": {
              "馬番": 1,
              "馬名": "ベイビークエスト",
              "スコア": 76.1,
              "役割": "軸馬候補"
            },
            "穴": {
              "馬番": 9,
              "馬名": "ノースラノビア",
              "スコア": 61.5,
              "役割": "穴馬候補"
            },
            "ワイドオッズ": null,
            "買い目": "1-9",
            "投資": 500
          },
          {
            "軸": {
              "馬番": 1,
              "馬名": "ベイビークエスト",
              "スコア": 76.1,
              "役割": "軸馬候補"
            },
            "穴": {
              "馬番": 7,
              "馬名": "フークアンビション",
              "スコア": 57.25,
              "役割": "穴馬候補"
            },
            "ワイドオッズ": null,
            "買い目": "1-7",
            "投資": 500
          }
        ],
        "複勝候補": [],
        "旧ロジック": {
          "旧_軸頭数": 3,
          "旧_相手頭数": 2,
          "旧_組み合わせ数": 10,
          "旧_投資額": 1000,
          "旧_買い目タイプ": "三連複フォーメーション(スコア順)"
        }
      },
      "status": "不的中",
      "predicted": [
        "1-3-5",
        "3-5-6",
        "3-5-8",
        "3-5-9",
        "3-5-7",
        "1-3-6",
        "1-3-8",
        "1-3-9",
        "1-3-7",
        "3-6-8",
        "3-6-9",
        "3-6-7",
        "1-5-8",
        "1-5-9",
        "1-5-7",
        "5-6-8",
        "5-6-9",
        "5-6-7",
        "1-6-8",
        "1-6-9",
        "6-8-9",
        "6-7-8",
        "7-8-9"
      ],
      "actual": [
        "2-4-6"
      ],
      "result_sanrenpuku": "2-4-6",
      "payout_sanrenpuku": 1490,
      "hit": false,
      "payout_missing": false,
      "investment": 2300,
      "return": 0,
      "profit": -2300,
      "payouts": {
        "単勝": 1100,
        "複勝": 130,
        "枠連": 2610,
        "馬連": 2650,
        "ワイド": 280,
        "枠単": 6260,
        "馬単": 6030,
        "三連複": 1490,
        "三連単": 16590
      },
      "horse_weights": [
        {
          "rank": 1,
          "horse_number": "2",
          "weight": "479(-5)"
        },
        {
          "rank": 2,
          "horse_number": "4",
          "weight": "488(-14)"
        },
        {
          "rank": 3,
          "horse_number": "6",
          "weight": "487(+3)"
        }
      ],
      "all_horses_result": [
        {
          "馬番": "2",
          "着順": 1,
          "人気": 6,
          "馬名": "メイクセンス",
          "馬体重": "479(-5)",
          "DASスコア": null,
          "役割": "予測外"
        },
        {
          "馬番": "4",
          "着順": 2,
          "人気": 4,
          "馬名": "デンテブリランテ",
          "馬体重": "488(-14)",
          "DASスコア": null,
          "役割": "予測外"
        },
        {
          "馬番": "6",
          "着順": 3,
          "人気": 1,
          "馬名": "アトレーヴフェイス",
          "馬体重": "487(+3)",
          "DASスコア": 63.25,
          "役割": "相手"
        },
        {
          "馬番": "5",
          "着順": 4,
          "人気": 5,
          "馬名": "グルーヴィン",
          "馬体重": "438(-8)",
          "DASスコア": 84.1,
          "役割": "軸"
        },
        {
          "馬番": "3",
          "着順": 5,
          "人気": 2,
          "馬名": "バーバリオン",
          "馬体重": "455(-1)",
          "DASスコア": 82.0,
          "役割": "軸"
        },
        {
          "馬番": "9",
          "着順": 6,
          "人気": 9,
          "馬名": "ノースラノビア",
          "馬体重": "513(+4)",
          "DASスコア": 61.5,
          "役割": "相手"
        },
        {
          "馬番": "7",
          "着順": 7,
          "人気": 7,
          "馬名": "フークアンビション",
          "馬体重": "487(+6)",
          "DASスコア": 57.25,
          "役割": "相手"
        },
        {
          "馬番": "1",
          "着順": 8,
          "人気": 3,
          "馬名": "ベイビークエスト",
          "馬体重": "481(+7)",
          "DASスコア": 76.1,
          "役割": "軸"
        },
        {
          "馬番": "8",
          "着順": 9,
          "人気": 8,
          "馬名": "デーレーシトロン",
          "馬体重": "441(-3)",
          "DASスコア": 69.5,
          "役割": "相手"
        }
      ],
      "race_verification": {
        "axis_best_rank": 4,
        "axis_in_top3": false,
        "93rule_pop_in_top3_count": 1,
        "93rule_pop_in_top3_rate": 33.3,
        "score_top1_rank": 4,
        "score_top2_rank": 5,
        "score_top1_in_top3": false,
        "predicted_in_top3_count": 1,
        "unpredicted_in_top3_count": 2,
        "miss_pattern": "軸外れ",
        "winner_popularity": 6,
        "is_upset": true,
        "predicted_synthetic_odds": 4.4,
        "actual_payout": 1490,
        "odds_ratio": 3.386,
        "opponent_in_top3_count": 1
      },
      "virtual_bets_result": {
        "複勝_軸1": {
          "type": "複勝",
          "投資": 300,
          "払戻": 0,
          "収支": -300,
          "的中": false
        },
        "複勝_軸2": {
          "type": "複勝",
          "投資": 300,
          "払戻": 0,
          "収支": -300,
          "的中": false
        },
        "ワイド_軸1-2": {
          "type": "ワイド",
          "投資": 500,
          "払戻": 0,
          "収支": -500,
          "的中": false
        },
        "馬連_軸1-2": {
          "type": "馬連",
          "投資": 500,
          "払戻": 0,
          "収支": -500,
          "的中": false
        }
      },
      "weather": "晴",
      "track_condition": "良",
      "predicted_pace": "ハイペース"
    },
    {
      "race_id": "202644031201",
      "venue": "大井",
      "race_num": "01",
      "race_name": "C3一二",
      "distance": 1600,
      "track": "ダ",
      "start_time": "11:00",
      "betting_plan": {
        "軸": [
          {
            "馬番": 5,
            "馬名": "ゴールドタリスマン",
            "人気": 6,
            "評価": "◎",
            "スコア": 81.0,
            "補正後スコア": 81.0,
            "内訳": {
              "馬体重増減": 60,
              "当日人気": 50,
              "経験値": 100,
              "騎手厩舎": 100,
              "距離馬場適性": 100,
              "脚質": 100
            },
            "根拠": "実績豊富、好騎手、適性抜群、展開有利、軸馬候補",
            "断層役割": "軸馬候補",
            "危険フラグ": false,
            "危険理由": []
          },
          {
            "馬番": 12,
            "馬名": "ジャスティンダイヤ",
            "人気": 1,
            "評価": "○",
            "スコア": 78.5,
            "補正後スコア": 78.5,
            "内訳": {
              "馬体重増減": 40,
              "当日人気": 100,
              "経験値": 100,
              "騎手厩舎": 50,
              "距離馬場適性": 100,
              "脚質": 70
            },
            "根拠": "前走1-2位人気、実績豊富、適性抜群、軸馬候補",
            "断層役割": "軸馬候補",
            "危険フラグ": false,
            "危険理由": []
          },
          {
            "馬番": 11,
            "馬名": "ノアサンサン",
            "人気": 4,
            "評価": "○",
            "スコア": 75.0,
            "補正後スコア": 75.0,
            "内訳": {
              "馬体重増減": 80,
              "当日人気": 70,
              "経験値": 100,
              "騎手厩舎": 50,
              "距離馬場適性": 100,
              "脚質": 85
            },
            "根拠": "前走3-5位人気、体重減で好調、実績豊富、適性抜群、軸馬候補",
            "断層役割": "軸馬候補",
            "危険フラグ": false,
            "危険理由": []
          }
        ],
        "対抗": [
          {
            "馬番": 8,
            "馬名": "ハカイシン",
            "人気": 2,
            "評価": "▲",
            "スコア": 63.4,
            "補正後スコア": 63.4,
            "根拠": "前走1-2位人気、実績豊富、適性抜群、軸馬候補",
            "断層役割": "軸馬候補",
            "斤量騎手ボーナス": 2,
            "斤量騎手詳細": {
              "斤量差": 0.0,
              "騎手替わり": "+2(騎手乗り替わり: 石川倭→鷹見陸)"
            }
          }
        ],
        "穴": [
          {
            "馬番": 10,
            "馬名": "マハーギータ",
            "人気": 13,
            "評価": "△",
            "スコア": 35.0,
            "補正後スコア": 35.0,
            "根拠": "実績豊富、穴馬候補",
            "断層役割": "穴馬候補",
            "斤量騎手ボーナス": 5,
            "斤量騎手詳細": {
              "斤量差": 0.0,
              "騎手替わり": "+5(穴馬騎手乗り替わり: 遠藤健太→東原悠善)"
            }
          },
          {
            "馬番": 4,
            "馬名": "ヴェルヴェーナ",
            "人気": 12,
            "評価": "△",
            "スコア": 27.0,
            "補正後スコア": 27.0,
            "根拠": "実績豊富、穴馬候補",
            "断層役割": "穴馬候補",
            "斤量騎手ボーナス": 0,
            "斤量騎手詳細": {
              "斤量差": 0.0
            }
          }
        ],
        "相手": [
          {
            "馬番": 8,
            "馬名": "ハカイシン",
            "評価": "△",
            "スコア": 63.4,
            "根拠": "前走1-2位人気、実績豊富、適性抜群、軸馬候補"
          },
          {
            "馬番": 10,
            "馬名": "マハーギータ",
            "評価": "△",
            "スコア": 35.0,
            "根拠": "実績豊富、穴馬候補"
          },
          {
            "馬番": 4,
            "馬名": "ヴェルヴェーナ",
            "評価": "△",
            "スコア": 27.0,
            "根拠": "実績豊富、穴馬候補"
          }
        ],
        "買い目タイプ": "三連複フォーメーション(断層役割ベース・精度改善v3)",
        "組み合わせ数": 17,
        "合成オッズ": 8.95,
        "合成オッズ_全体": 1.17,
        "合成オッズ_方法": "actual",
        "賭け金調整": "コア合成オッズ8.95倍(5倍以上→200円/点)",
        "全買い目": [
          "5-11-12",
          "5-8-12",
          "5-10-12",
          "4-5-12",
          "5-8-11",
          "5-10-11",
          "4-5-11",
          "5-8-10",
          "4-5-8",
          "8-11-12",
          "10-11-12",
          "4-11-12",
          "8-10-12",
          "4-8-12",
          "8-10-11",
          "4-8-11",
          "4-8-10"
        ],
        "穴ボックス発動": false,
        "穴ボックス_upset_score": 10,
        "穴ボックス_upset_理由": [
          "波乱度:中(+10)"
        ],
        "穴ボックス_買い目": [],
        "穴ボックス_追加点数": 0,
        "相手ボックス_買い目": [
          "4-8-10"
        ],
        "相手ボックス_追加点数": 1,
        "ワイド候補": [
          {
            "軸": {
              "馬番": 12,
              "馬名": "ジャスティンダイヤ",
              "スコア": 78.5,
              "役割": "軸馬候補"
            },
            "穴": {
              "馬番": 4,
              "馬名": "ヴェルヴェーナ",
              "スコア": 27.0,
              "役割": "穴馬候補"
            },
            "ワイドオッズ": null,
            "買い目": "12-4",
            "投資": 500
          },
          {
            "軸": {
              "馬番": 12,
              "馬名": "ジャスティンダイヤ",
              "スコア": 78.5,
              "役割": "軸馬候補"
            },
            "穴": {
              "馬番": 10,
              "馬名": "マハーギータ",
              "スコア": 35.0,
              "役割": "穴馬候補"
            },
            "ワイドオッズ": null,
            "買い目": "12-10",
            "投資": 500
          }
        ],
        "複勝候補": [],
        "旧ロジック": {
          "旧_軸頭数": 3,
          "旧_相手頭数": 4,
          "旧_組み合わせ数": 31,
          "旧_投資額": 3100,
          "旧_買い目タイプ": "三連複フォーメーション(スコア順)"
        }
      },
      "status": "不的中",
      "predicted": [
        "5-11-12",
        "5-8-12",
        "5-10-12",
        "4-5-12",
        "5-8-11",
        "5-10-11",
        "4-5-11",
        "5-8-10",
        "4-5-8",
        "8-11-12",
        "10-11-12",
        "4-11-12",
        "8-10-12",
        "4-8-12",
        "8-10-11",
        "4-8-11",
        "4-8-10"
      ],
      "actual": [
        "8-12-13"
      ],
      "result_sanrenpuku": "8-12-13",
      "payout_sanrenpuku": 630,
      "hit": false,
      "payout_missing": false,
      "investment": 3400,
      "return": 0,
      "profit": -3400,
      "payouts": {
        "単勝": 380,
        "複勝": 100,
        "枠連": 240,
        "馬連": 330,
        "ワイド": 150,
        "枠単": 490,
        "馬単": 930,
        "三連複": 630,
        "三連単": 3300
      },
      "horse_weights": [
        {
          "rank": 1,
          "horse_number": "8",
          "weight": "549(0)"
        },
        {
          "rank": 2,
          "horse_number": "12",
          "weight": "523(+8)"
        },
        {
          "rank": 3,
          "horse_number": "13",
          "weight": "484(-1)"
        }
      ],
      "all_horses_result": [
        {
          "馬番": "8",
          "着順": 1,
          "人気": 2,
          "馬名": "ハカイシン",
          "馬体重": "549(0)",
          "DASスコア": 63.4,
          "役割": "相手"
        },
        {
          "馬番": "12",
          "着順": 2,
          "人気": 1,
          "馬名": "ジャスティンダイヤ",
          "馬体重": "523(+8)",
          "DASスコア": 78.5,
          "役割": "軸"
        },
        {
          "馬番": "13",
          "着順": 3,
          "人気": 3,
          "馬名": "ミチノシチリア",
          "馬体重": "484(-1)",
          "DASスコア": null,
          "役割": "予測外"
        },
        {
          "馬番": "9",
          "着順": 4,
          "人気": 10,
          "馬名": "マキズシトイナ",
          "馬体重": "493(+3)",
          "DASスコア": null,
          "役割": "予測外"
        },
        {
          "馬番": "11",
          "着順": 5,
          "人気": 5,
          "馬名": "ノアサンサン",
          "馬体重": "460(-5)",
          "DASスコア": 75.0,
          "役割": "軸"
        },
        {
          "馬番": "2",
          "着順": 6,
          "人気": 8,
          "馬名": "ファインデイ",
          "馬体重": "470(+4)",
          "DASスコア": null,
          "役割": "予測外"
        },
        {
          "馬番": "5",
          "着順": 7,
          "人気": 4,
          "馬名": "ゴールドタリスマン",
          "馬体重": "436(-2)",
          "DASスコア": 81.0,
          "役割": "軸"
        },
        {
          "馬番": "3",
          "着順": 8,
          "人気": 9,
          "馬名": "ノリサムソン",
          "馬体重": "489(+5)",
          "DASスコア": null,
          "役割": "予測外"
        },
        {
          "馬番": "7",
          "着順": 9,
          "人気": 6,
          "馬名": "キバルスター",
          "馬体重": "489(-1)",
          "DASスコア": null,
          "役割": "予測外"
        },
        {
          "馬番": "1",
          "着順": 10,
          "人気": 7,
          "馬名": "シルフラ",
          "馬体重": "452(+7)",
          "DASスコア": null,
          "役割": "予測外"
        },
        {
          "馬番": "10",
          "着順": 11,
          "人気": 12,
          "馬名": "マハーギータ",
          "馬体重": "428(0)",
          "DASスコア": 35.0,
          "役割": "相手"
        },
        {
          "馬番": "4",
          "着順": 12,
          "人気": 11,
          "馬名": "ヴェルヴェーナ",
          "馬体重": "465(+7)",
          "DASスコア": 27.0,
          "役割": "相手"
        }
      ],
      "race_verification": {
        "axis_best_rank": 2,
        "axis_in_top3": true,
        "93rule_pop_in_top3_count": 3,
        "93rule_pop_in_top3_rate": 100.0,
        "score_top1_rank": 7,
        "score_top2_rank": 2,
        "score_top1_in_top3": false,
        "predicted_in_top3_count": 2,
        "unpredicted_in_top3_count": 1,
        "miss_pattern": "穴台頭",
        "winner_popularity": 2,
        "is_upset": false,
        "predicted_synthetic_odds": 8.95,
        "actual_payout": 630,
        "odds_ratio": 0.704,
        "opponent_in_top3_count": 1
      },
      "virtual_bets_result": {
        "複勝_軸1": {
          "type": "複勝",
          "投資": 300,
          "払戻": 0,
          "収支": -300,
          "的中": false
        },
        "複勝_軸2": {
          "type": "複勝",
          "投資": 300,
          "払戻": 300,
          "収支": 0,
          "的中": true
        },
        "ワイド_軸1-2": {
          "type": "ワイド",
          "投資": 500,
          "払戻": 0,
          "収支": -500,
          "的中": false
        },
        "馬連_軸1-2": {
          "type": "馬連",
          "投資": 500,
          "払戻": 0,
          "収支": -500,
          "的中": false
        }
      },
      "weather": "晴",
      "track_condition": "良",
      "predicted_pace": "スローペース"
    },
    {
      "race_id": "202651031209",
      "venue": "姫路",
      "race_num": "09",
      "race_name": "飲んで応援!ひょうごの酪農賞C1",
      "distance": 1800,
      "track": "ダ",
      "start_time": "14:55",
      "betting_plan": {
        "軸": [
          {
            "馬番": 1,
            "馬名": "グランゲレーロ",
            "人気": 8,
            "評価": "◎",
            "スコア": 60.65,
            "補正後スコア": 66.65,
            "内訳": {
              "馬体重増減": 60,
              "当日人気": 50,
              "経験値": 100,
              "騎手厩舎": 25,
              "距離馬場適性": 92,
              "脚質": 100
            },
            "根拠": "実績豊富、適性抜群、展開有利、軸馬候補",
            "断層役割": "軸馬候補",
            "危険フラグ": false,
            "危険理由": []
          },
          {
            "馬番": 8,
            "馬名": "スマートエクシード",
            "人気": 7,
            "評価": "○",
            "スコア": 60.75,
            "補正後スコア": 63.75,
            "内訳": {
              "馬体重増減": 60,
              "当日人気": 50,
              "経験値": 100,
              "騎手厩舎": 25,
              "距離馬場適性": 100,
              "脚質": 85
            },
            "根拠": "実績豊富、適性抜群、軸馬候補",
            "断層役割": "軸馬候補",
            "危険フラグ": false,
            "危険理由": []
          },
          {
            "馬番": 6,
            "馬名": "マカセナハレ",
            "人気": 2,
            "評価": "○",
            "スコア": 63.85,
            "補正後スコア": 60.85,
            "内訳": {
              "馬体重増減": 20,
              "当日人気": 90,
              "経験値": 80,
              "騎手厩舎": 25,
              "距離馬場適性": 88,
              "脚質": 70
            },
            "根拠": "前走1-2位人気、体重増で不安、実績豊富、軸馬候補",
            "断層役割": "軸馬候補",
            "危険フラグ": false,
            "危険理由": []
          }
        ],
        "対抗": [
          {
            "馬番": 5,
            "馬名": "ギャランドゥ",
            "人気": 1,
            "評価": "▲",
            "スコア": 59.85,
            "補正後スコア": 56.85,
            "根拠": "前走1-2位人気、体重減で好調、実績豊富、軸馬候補",
            "断層役割": "軸馬候補",
            "斤量騎手ボーナス": 2,
            "斤量騎手詳細": {
              "斤量差": 0.0,
              "騎手替わり": "+2(騎手乗り替わり: 下原理→吉村智洋)"
            }
          },
          {
            "馬番": 7,
            "馬名": "テクノグルーヴ",
            "人気": 3,
            "評価": "▲",
            "スコア": 43.0,
            "補正後スコア": 40.0,
            "根拠": "前走3-5位人気、実績豊富、軸馬候補",
            "断層役割": "軸馬候補",
            "斤量騎手ボーナス": 0,
            "斤量騎手詳細": {
              "斤量差": 0.0
            }
          }
        ],
        "穴": [
          {
            "馬番": 2,
            "馬名": "ニシノオールマイト",
            "人気": 9,
            "評価": "△",
            "スコア": 53.0,
            "補正後スコア": 50.0,
            "根拠": "実績豊富、適性抜群、穴馬候補",
            "断層役割": "穴馬候補",
            "斤量騎手ボーナス": -5,
            "斤量騎手詳細": {
              "斤量差": 1.0,
              "斤量ボーナス": "-5(増量)"
            }
          },
          {
            "馬番": 4,
            "馬名": "マイネルイヴィンス",
            "人気": 10,
            "評価": "△",
            "スコア": 37.0,
            "補正後スコア": 34.0,
            "根拠": "実績豊富、穴馬候補",
            "断層役割": "穴馬候補",
            "斤量騎手ボーナス": 0,
            "斤量騎手詳細": {
              "斤量差": 1.0,
              "斤量ボーナス": "-5(増量)",
              "騎手替わり": "+5(穴馬騎手乗り替わり: 吉村智洋→杉浦健太)"
            }
          }
        ],
        "相手": [
          {
            "馬番": 5,
            "馬名": "ギャランドゥ",
            "評価": "△",
            "スコア": 59.85,
            "根拠": "前走1-2位人気、体重減で好調、実績豊富、軸馬候補"
          },
          {
            "馬番": 7,
            "馬名": "テクノグルーヴ",
            "評価": "△",
            "スコア": 43.0,
            "根拠": "前走3-5位人気、実績豊富、軸馬候補"
          },
          {
            "馬番": 2,
            "馬名": "ニシノオールマイト",
            "評価": "△",
            "スコア": 53.0,
            "根拠": "実績豊富、適性抜群、穴馬候補"
          },
          {
            "馬番": 4,
            "馬名": "マイネルイヴィンス",
            "評価": "△",
            "スコア": 37.0,
            "根拠": "実績豊富、穴馬候補"
          }
        ],
        "買い目タイプ": "三連複フォーメーション(断層役割ベース・精度改善v3)",
        "組み合わせ数": 23,
        "合成オッズ": 7.05,
        "合成オッズ_全体": 1.03,
        "合成オッズ_方法": "actual",
        "賭け金調整": "コア合成オッズ7.05倍(5倍以上→200円/点)",
        "全買い目": [
          "1-6-8",
          "1-5-8",
          "1-7-8",
          "1-2-8",
          "1-4-8",
          "1-5-6",
          "1-6-7",
          "1-2-6",
          "1-4-6",
          "1-5-7",
          "1-2-5",
          "1-4-5",
          "1-2-7",
          "1-4-7",
          "5-6-8",
          "6-7-8",
          "2-6-8",
          "4-6-8",
          "5-7-8",
          "2-5-8",
          "2-5-7",
          "2-4-5",
          "4-5-7"
        ],
        "穴ボックス発動": false,
        "穴ボックス_upset_score": 10,
        "穴ボックス_upset_理由": [
          "波乱度:中(+10)"
        ],
        "穴ボックス_買い目": [],
        "穴ボックス_追加点数": 0,
        "相手ボックス_買い目": [
          "2-5-7",
          "2-4-5",
          "4-5-7"
        ],
        "相手ボックス_追加点数": 3,
        "ワイド候補": [
          {
            "軸": {
              "馬番": 5,
              "馬名": "ギャランドゥ",
              "スコア": 59.85,
              "役割": "軸馬候補"
            },
            "穴": {
              "馬番": 2,
              "馬名": "ニシノオールマイト",
              "スコア": 53.0,
              "役割": "穴馬候補"
            },
            "ワイドオッズ": null,
            "買い目": "5-2",
            "投資": 500
          },
          {
            "軸": {
              "馬番": 5,
              "馬名": "ギャランドゥ",
              "スコア": 59.85,
              "役割": "軸馬候補"
            },
            "穴": {
              "馬番": 4,
              "馬名": "マイネルイヴィンス",
              "スコア": 37.0,
              "役割": "穴馬候補"
            },
            "ワイドオッズ": null,
            "買い目": "5-4",
            "投資": 500
          }
        ],
        "複勝候補": [],
        "旧ロジック": {
          "旧_軸頭数": 3,
          "旧_相手頭数": 3,
          "旧_組み合わせ数": 19,
          "旧_投資額": 1900,
          "旧_買い目タイプ": "三連複フォーメーション(スコア順)"
        }
      },
      "status": "的中",
      "predicted": [
        "1-6-8",
        "1-5-8",
        "1-7-8",
        "1-2-8",
        "1-4-8",
        "1-5-6",
        "1-6-7",
        "1-2-6",
        "1-4-6",
        "1-5-7",
        "1-2-5",
        "1-4-5",
        "1-2-7",
        "1-4-7",
        "5-6-8",
        "6-7-8",
        "2-6-8",
        "4-6-8",
        "5-7-8",
        "2-5-8",
        "2-5-7",
        "2-4-5",
        "4-5-7"
      ],
      "actual": [
        "5-8-6"
      ],
      "result_sanrenpuku": "5-8-6",
      "payout_sanrenpuku": 1060,
      "hit": true,
      "payout_missing": false,
      "investment": 4600,
      "return": 1060,
      "profit": -3540,
      "payouts": {
        "単勝": 170,
        "複勝": 100,
        "枠連": 400,
        "馬連": 870,
        "ワイド": 190,
        "馬単": 1040,
        "三連複": 1060,
        "三連単": 4890
      },
      "horse_weights": [
        {
          "rank": 1,
          "horse_number": "5",
          "weight": "456(-2)"
        },
        {
          "rank": 2,
          "horse_number": "8",
          "weight": "500(0)"
        },
        {
          "rank": 3,
          "horse_number": "6",
          "weight": "497(+6)"
        }
      ],
      "all_horses_result": [
        {
          "馬番": "5",
          "着順": 1,
          "人気": 1,
          "馬名": "ギャランドゥ",
          "馬体重": "456(-2)",
          "DASスコア": 59.85,
          "役割": "相手"
        },
        {
          "馬番": "8",
          "着順": 2,
          "人気": 4,
          "馬名": "スマートエクシード",
          "馬体重": "500(0)",
          "DASスコア": 60.75,
          "役割": "軸"
        },
        {
          "馬番": "6",
          "着順": 3,
          "人気": 2,
          "馬名": "マカセナハレ",
          "馬体重": "497(+6)",
          "DASスコア": 63.85,
          "役割": "軸"
        },
        {
          "馬番": "3",
          "着順": 4,
          "人気": 5,
          "馬名": "サムタイムアゴー",
          "馬体重": "447(-5)",
          "DASスコア": null,
          "役割": "予測外"
        },
        {
          "馬番": "9",
          "着順": 5,
          "人気": 6,
          "馬名": "ワンダーグリー",
          "馬体重": "447(+4)",
          "DASスコア": null,
          "役割": "予測外"
        },
        {
          "馬番": "7",
          "着順": 6,
          "人気": 3,
          "馬名": "テクノグルーヴ",
          "馬体重": "486(+4)",
          "DASスコア": 43.0,
          "役割": "相手"
        },
        {
          "馬番": "10",
          "着順": 7,
          "人気": 8,
          "馬名": "ムーンレイデオ",
          "馬体重": "434(+1)",
          "DASスコア": null,
          "役割": "予測外"
        },
        {
          "馬番": "1",
          "着順": 8,
          "人気": 7,
          "馬名": "グランゲレーロ",
          "馬体重": "476(0)",
          "DASスコア": 60.65,
          "役割": "軸"
        },
        {
          "馬番": "2",
          "着順": 9,
          "人気": 9,
          "馬名": "ニシノオールマイト",
          "馬体重": "497(-1)",
          "DASスコア": 53.0,
          "役割": "相手"
        },
        {
          "馬番": "4",
          "着順": 10,
          "人気": 10,
          "馬名": "マイネルイヴィンス",
          "馬体重": "513(+1)",
          "DASスコア": 37.0,
          "役割": "相手"
        }
      ],
      "race_verification": {
        "axis_best_rank": 2,
        "axis_in_top3": true,
        "93rule_pop_in_top3_count": 2,
        "93rule_pop_in_top3_rate": 66.7,
        "score_top1_rank": 3,
        "score_top2_rank": 2,
        "score_top1_in_top3": true,
        "predicted_in_top3_count": 3,
        "unpredicted_in_top3_count": 0,
        "miss_pattern": "的中",
        "winner_popularity": 1,
        "is_upset": false,
        "predicted_synthetic_odds": 7.05,
        "actual_payout": 1060,
        "odds_ratio": 1.504,
        "opponent_in_top3_count": 1
      },
      "virtual_bets_result": {
        "複勝_軸1": {
          "type": "複勝",
          "投資": 300,
          "払戻": 0,
          "収支": -300,
          "的中": false
        },
        "複勝_軸2": {
          "type": "複勝",
          "投資": 300,
          "払戻": 300,
          "収支": 0,
          "的中": true
        },
        "ワイド_軸1-2": {
          "type": "ワイド",
          "投資": 500,
          "払戻": 0,
          "収支": -500,
          "的中": false
        },
        "馬連_軸1-2": {
          "type": "馬連",
          "投資": 500,
          "払戻": 0,
          "収支": -500,
          "的中": false
        }
      },
      "weather": "晴",
      "track_condition": "良",
      "predicted_pace": "スローペース"
    }
  ]
}