{
  "ymd": "20260529",
  "generated_at": "2026-05-28 16:45:31",
  "logic_version": "v12",
  "summary": {
    "total_races": 5,
    "hit_count": 0,
    "miss_count": 5,
    "hit_rate": 0.0,
    "total_investment": 3700,
    "total_payout": 0,
    "net_profit": -3700,
    "recovery_rate": 0.0
  },
  "details": [
    {
      "race_id": "202642052910",
      "race_name": "鈴蘭特別(B3)",
      "venue": "浦和",
      "prediction_type": "recommend",
      "investment": 2100,
      "combo_count": 21,
      "per_bet_investment": 100,
      "synthetic_odds": 4.5,
      "hit": false,
      "hit_type": null,
      "payout": 0,
      "profit": -2100,
      "reason": "着順データなし"
    },
    {
      "race_id": "202647052908",
      "race_name": "C3組",
      "venue": "笠松",
      "prediction_type": "reference",
      "investment": 400,
      "combo_count": 4,
      "per_bet_investment": 100,
      "synthetic_odds": 2.25,
      "hit": false,
      "hit_type": null,
      "payout": 0,
      "profit": -400,
      "reason": "着順データなし"
    },
    {
      "race_id": "202647052910",
      "race_name": "キキョウ特別(A)",
      "venue": "笠松",
      "prediction_type": "reference",
      "investment": 400,
      "combo_count": 4,
      "per_bet_investment": 100,
      "synthetic_odds": 2.4,
      "hit": false,
      "hit_type": null,
      "payout": 0,
      "profit": -400,
      "reason": "着順データなし"
    },
    {
      "race_id": "202647052912",
      "race_name": "C級サバイバル",
      "venue": "笠松",
      "prediction_type": "reference",
      "investment": 400,
      "combo_count": 4,
      "per_bet_investment": 100,
      "synthetic_odds": 2.5,
      "hit": false,
      "hit_type": null,
      "payout": 0,
      "profit": -400,
      "reason": "着順データなし"
    },
    {
      "race_id": "202650052902",
      "race_name": "C3二",
      "venue": "園田",
      "prediction_type": "reference",
      "investment": 400,
      "combo_count": 4,
      "per_bet_investment": 100,
      "synthetic_odds": 2.15,
      "hit": false,
      "hit_type": null,
      "payout": 0,
      "profit": -400,
      "reason": "着順データなし"
    }
  ]
}