{
  "ymd": "20260226",
  "generated_at": "2026-03-02 17:10:24",
  "logic_version": "v12",
  "summary": {
    "total_races": 19,
    "hit_count": 0,
    "miss_count": 19,
    "hit_rate": 0.0,
    "total_investment": 38000,
    "total_payout": 0,
    "net_profit": -38000,
    "recovery_rate": 0.0
  },
  "details": [
    {
      "race_id": "202648022603",
      "race_name": "C17組",
      "venue": "名古屋",
      "investment": 2000,
      "combo_count": 15,
      "synthetic_odds": 6.17,
      "hit": false,
      "hit_type": null,
      "payout": 0,
      "profit": -2000,
      "reason": "不的中 (実際: 11-10-3, 15点中)"
    },
    {
      "race_id": "202642022605",
      "race_name": "C2七八",
      "venue": "浦和",
      "investment": 2000,
      "combo_count": 15,
      "synthetic_odds": 10.15,
      "hit": false,
      "hit_type": null,
      "payout": 0,
      "profit": -2000,
      "reason": "結果データなし"
    },
    {
      "race_id": "202642022612",
      "race_name": "春の月特別(B2B3)",
      "venue": "浦和",
      "investment": 2000,
      "combo_count": 15,
      "synthetic_odds": 6.65,
      "hit": false,
      "hit_type": null,
      "payout": 0,
      "profit": -2000,
      "reason": "結果データなし"
    },
    {
      "race_id": "202648022610",
      "race_name": "フェブラリードリーム戦(3歳)",
      "venue": "名古屋",
      "investment": 2000,
      "combo_count": 15,
      "synthetic_odds": 6.4,
      "hit": false,
      "hit_type": null,
      "payout": 0,
      "profit": -2000,
      "reason": "結果データなし"
    },
    {
      "race_id": "202648022605",
      "race_name": "C15組",
      "venue": "名古屋",
      "investment": 2000,
      "combo_count": 15,
      "synthetic_odds": 6.4,
      "hit": false,
      "hit_type": null,
      "payout": 0,
      "profit": -2000,
      "reason": "結果データなし"
    },
    {
      "race_id": "202648022611",
      "race_name": "スプリングカップ重賞",
      "venue": "名古屋",
      "investment": 2000,
      "combo_count": 15,
      "synthetic_odds": 5.83,
      "hit": false,
      "hit_type": null,
      "payout": 0,
      "profit": -2000,
      "reason": "不的中 (実際: 11-2-7, 15点中)"
    },
    {
      "race_id": "202648022606",
      "race_name": "C14組",
      "venue": "名古屋",
      "investment": 2000,
      "combo_count": 15,
      "synthetic_odds": 5.83,
      "hit": false,
      "hit_type": null,
      "payout": 0,
      "profit": -2000,
      "reason": "結果データなし"
    },
    {
      "race_id": "202651022610",
      "race_name": "青馬ひすみ☆配信記念B2",
      "venue": "姫路",
      "investment": 2000,
      "combo_count": 15,
      "synthetic_odds": 9.91,
      "hit": false,
      "hit_type": null,
      "payout": 0,
      "profit": -2000,
      "reason": "結果データなし"
    },
    {
      "race_id": "202651022609",
      "race_name": "祝30周年!SPAT4賞C2",
      "venue": "姫路",
      "investment": 2000,
      "combo_count": 15,
      "synthetic_odds": 6.54,
      "hit": false,
      "hit_type": null,
      "payout": 0,
      "profit": -2000,
      "reason": "結果データなし"
    },
    {
      "race_id": "202642022609",
      "race_name": "ツインホープ特別(3歳)",
      "venue": "浦和",
      "investment": 2000,
      "combo_count": 15,
      "synthetic_odds": 9.91,
      "hit": false,
      "hit_type": null,
      "payout": 0,
      "profit": -2000,
      "reason": "結果データなし"
    },
    {
      "race_id": "202651022604",
      "race_name": "有年楢原7ハロンC2二",
      "venue": "姫路",
      "investment": 2000,
      "combo_count": 15,
      "synthetic_odds": 9.59,
      "hit": false,
      "hit_type": null,
      "payout": 0,
      "profit": -2000,
      "reason": "結果データなし"
    },
    {
      "race_id": "202651022607",
      "race_name": "C2一",
      "venue": "姫路",
      "investment": 2000,
      "combo_count": 15,
      "synthetic_odds": 9.08,
      "hit": false,
      "hit_type": null,
      "payout": 0,
      "profit": -2000,
      "reason": "結果データなし"
    },
    {
      "race_id": "202642022601",
      "race_name": "C3三四",
      "venue": "浦和",
      "investment": 2000,
      "combo_count": 15,
      "synthetic_odds": 6.4,
      "hit": false,
      "hit_type": null,
      "payout": 0,
      "profit": -2000,
      "reason": "結果データなし"
    },
    {
      "race_id": "202642022603",
      "race_name": "浦和800ラウンド(3歳)",
      "venue": "浦和",
      "investment": 2000,
      "combo_count": 15,
      "synthetic_odds": 5.83,
      "hit": false,
      "hit_type": null,
      "payout": 0,
      "profit": -2000,
      "reason": "結果データなし"
    },
    {
      "race_id": "202651022603",
      "race_name": "3歳C1",
      "venue": "姫路",
      "investment": 2000,
      "combo_count": 15,
      "synthetic_odds": 8.37,
      "hit": false,
      "hit_type": null,
      "payout": 0,
      "profit": -2000,
      "reason": "結果データなし"
    },
    {
      "race_id": "202648022601",
      "race_name": "小山記念(C)",
      "venue": "名古屋",
      "investment": 2000,
      "combo_count": 15,
      "synthetic_odds": 6.54,
      "hit": false,
      "hit_type": null,
      "payout": 0,
      "profit": -2000,
      "reason": "結果データなし"
    },
    {
      "race_id": "202642022604",
      "race_name": "C3三四",
      "venue": "浦和",
      "investment": 2000,
      "combo_count": 15,
      "synthetic_odds": 6.67,
      "hit": false,
      "hit_type": null,
      "payout": 0,
      "profit": -2000,
      "reason": "結果データなし"
    },
    {
      "race_id": "202651022601",
      "race_name": "C3二",
      "venue": "姫路",
      "investment": 2000,
      "combo_count": 15,
      "synthetic_odds": 9.08,
      "hit": false,
      "hit_type": null,
      "payout": 0,
      "profit": -2000,
      "reason": "結果データなし"
    },
    {
      "race_id": "202651022612",
      "race_name": "初コラボも全部まとめて馬九行久!青馬ひす(B2C1)",
      "venue": "姫路",
      "investment": 2000,
      "combo_count": 15,
      "synthetic_odds": 9.91,
      "hit": false,
      "hit_type": null,
      "payout": 0,
      "profit": -2000,
      "reason": "結果データなし"
    }
  ]
}