{
  "ymd": "20260404",
  "generated_at": "2026-04-04 13:43:34",
  "logic_version": "v12",
  "summary": {
    "total_races": 2,
    "hit_count": 0,
    "miss_count": 2,
    "hit_rate": 0.0,
    "total_investment": 800,
    "total_payout": 0,
    "net_profit": -800,
    "recovery_rate": 0.0
  },
  "details": [
    {
      "race_id": "202606030311",
      "race_name": "ダービー卿CT",
      "venue": "中山",
      "prediction_type": "reference",
      "investment": 400,
      "combo_count": 4,
      "per_bet_investment": 100,
      "synthetic_odds": 3.23,
      "hit": false,
      "hit_type": null,
      "payout": 0,
      "profit": -400,
      "reason": "不的中 (実際: 11-16-8, 4点中)"
    },
    {
      "race_id": "202609020310",
      "race_name": "ポラリスS",
      "venue": "阪神",
      "prediction_type": "reference",
      "investment": 400,
      "combo_count": 4,
      "per_bet_investment": 100,
      "synthetic_odds": 3.45,
      "hit": false,
      "hit_type": null,
      "payout": 0,
      "profit": -400,
      "reason": "不的中 (実際: 5-7-12, 4点中)"
    }
  ]
}