{
  "ymd": "20260508",
  "generated_at": "2026-05-07 15:23:17",
  "logic_version": "v12",
  "summary": {
    "total_races": 1,
    "hit_count": 0,
    "miss_count": 1,
    "hit_rate": 0.0,
    "total_investment": 2100,
    "total_payout": 0,
    "net_profit": -2100,
    "recovery_rate": 0.0
  },
  "details": [
    {
      "race_id": "202648050803",
      "race_name": "祝45歳!キミとの未来は最高(C)",
      "venue": "名古屋",
      "prediction_type": "recommend",
      "investment": 2100,
      "combo_count": 21,
      "per_bet_investment": 100,
      "synthetic_odds": 4.7,
      "hit": false,
      "hit_type": null,
      "payout": 0,
      "profit": -2100,
      "reason": "着順データなし"
    }
  ]
}