{
  "date": "20260402",
  "generated_at": "2026-04-01T00:03:28.810483+09:00",
  "is_weekend": false,
  "weekday": "木",
  "total_race_count": 35,
  "total_venues": 3,
  "jra_races": 0,
  "nar_races": 35,
  "race_ids": [
    "202643040201",
    "202643040202",
    "202643040203",
    "202643040204",
    "202643040205",
    "202643040206",
    "202643040207",
    "202643040208",
    "202643040209",
    "202643040210",
    "202643040211",
    "202643040212",
    "202647040201",
    "202647040202",
    "202647040203",
    "202647040204",
    "202647040205",
    "202647040206",
    "202647040207",
    "202647040208",
    "202647040209",
    "202647040210",
    "202647040211",
    "202650040201",
    "202650040202",
    "202650040203",
    "202650040204",
    "202650040205",
    "202650040206",
    "202650040207",
    "202650040208",
    "202650040209",
    "202650040210",
    "202650040211",
    "202650040212"
  ],
  "selected_predictions": [
    {
      "race_id": "202643040201",
      "race_info": {
        "venue": "船橋",
        "venue_code": "43",
        "venue_type": "NAR",
        "race_no": 1,
        "レース名": "1R"
      }
    },
    {
      "race_id": "202643040202",
      "race_info": {
        "venue": "船橋",
        "venue_code": "43",
        "venue_type": "NAR",
        "race_no": 2,
        "レース名": "2R"
      }
    },
    {
      "race_id": "202643040203",
      "race_info": {
        "venue": "船橋",
        "venue_code": "43",
        "venue_type": "NAR",
        "race_no": 3,
        "レース名": "3R"
      }
    },
    {
      "race_id": "202643040204",
      "race_info": {
        "venue": "船橋",
        "venue_code": "43",
        "venue_type": "NAR",
        "race_no": 4,
        "レース名": "4R"
      }
    },
    {
      "race_id": "202643040205",
      "race_info": {
        "venue": "船橋",
        "venue_code": "43",
        "venue_type": "NAR",
        "race_no": 5,
        "レース名": "5R"
      }
    },
    {
      "race_id": "202643040206",
      "race_info": {
        "venue": "船橋",
        "venue_code": "43",
        "venue_type": "NAR",
        "race_no": 6,
        "レース名": "6R"
      }
    },
    {
      "race_id": "202643040207",
      "race_info": {
        "venue": "船橋",
        "venue_code": "43",
        "venue_type": "NAR",
        "race_no": 7,
        "レース名": "7R"
      }
    },
    {
      "race_id": "202643040208",
      "race_info": {
        "venue": "船橋",
        "venue_code": "43",
        "venue_type": "NAR",
        "race_no": 8,
        "レース名": "8R"
      }
    },
    {
      "race_id": "202643040209",
      "race_info": {
        "venue": "船橋",
        "venue_code": "43",
        "venue_type": "NAR",
        "race_no": 9,
        "レース名": "9R"
      }
    },
    {
      "race_id": "202643040210",
      "race_info": {
        "venue": "船橋",
        "venue_code": "43",
        "venue_type": "NAR",
        "race_no": 10,
        "レース名": "10R"
      }
    },
    {
      "race_id": "202643040211",
      "race_info": {
        "venue": "船橋",
        "venue_code": "43",
        "venue_type": "NAR",
        "race_no": 11,
        "レース名": "11R"
      }
    },
    {
      "race_id": "202643040212",
      "race_info": {
        "venue": "船橋",
        "venue_code": "43",
        "venue_type": "NAR",
        "race_no": 12,
        "レース名": "12R"
      }
    },
    {
      "race_id": "202647040201",
      "race_info": {
        "venue": "笠松",
        "venue_code": "47",
        "venue_type": "NAR",
        "race_no": 1,
        "レース名": "1R"
      }
    },
    {
      "race_id": "202647040202",
      "race_info": {
        "venue": "笠松",
        "venue_code": "47",
        "venue_type": "NAR",
        "race_no": 2,
        "レース名": "2R"
      }
    },
    {
      "race_id": "202647040203",
      "race_info": {
        "venue": "笠松",
        "venue_code": "47",
        "venue_type": "NAR",
        "race_no": 3,
        "レース名": "3R"
      }
    },
    {
      "race_id": "202647040204",
      "race_info": {
        "venue": "笠松",
        "venue_code": "47",
        "venue_type": "NAR",
        "race_no": 4,
        "レース名": "4R"
      }
    },
    {
      "race_id": "202647040205",
      "race_info": {
        "venue": "笠松",
        "venue_code": "47",
        "venue_type": "NAR",
        "race_no": 5,
        "レース名": "5R"
      }
    },
    {
      "race_id": "202647040206",
      "race_info": {
        "venue": "笠松",
        "venue_code": "47",
        "venue_type": "NAR",
        "race_no": 6,
        "レース名": "6R"
      }
    },
    {
      "race_id": "202647040207",
      "race_info": {
        "venue": "笠松",
        "venue_code": "47",
        "venue_type": "NAR",
        "race_no": 7,
        "レース名": "7R"
      }
    },
    {
      "race_id": "202647040208",
      "race_info": {
        "venue": "笠松",
        "venue_code": "47",
        "venue_type": "NAR",
        "race_no": 8,
        "レース名": "8R"
      }
    },
    {
      "race_id": "202647040209",
      "race_info": {
        "venue": "笠松",
        "venue_code": "47",
        "venue_type": "NAR",
        "race_no": 9,
        "レース名": "9R"
      }
    },
    {
      "race_id": "202647040210",
      "race_info": {
        "venue": "笠松",
        "venue_code": "47",
        "venue_type": "NAR",
        "race_no": 10,
        "レース名": "10R"
      }
    },
    {
      "race_id": "202647040211",
      "race_info": {
        "venue": "笠松",
        "venue_code": "47",
        "venue_type": "NAR",
        "race_no": 11,
        "レース名": "11R"
      }
    },
    {
      "race_id": "202650040201",
      "race_info": {
        "venue": "園田",
        "venue_code": "50",
        "venue_type": "NAR",
        "race_no": 1,
        "レース名": "1R"
      }
    },
    {
      "race_id": "202650040202",
      "race_info": {
        "venue": "園田",
        "venue_code": "50",
        "venue_type": "NAR",
        "race_no": 2,
        "レース名": "2R"
      }
    },
    {
      "race_id": "202650040203",
      "race_info": {
        "venue": "園田",
        "venue_code": "50",
        "venue_type": "NAR",
        "race_no": 3,
        "レース名": "3R"
      }
    },
    {
      "race_id": "202650040204",
      "race_info": {
        "venue": "園田",
        "venue_code": "50",
        "venue_type": "NAR",
        "race_no": 4,
        "レース名": "4R"
      }
    },
    {
      "race_id": "202650040205",
      "race_info": {
        "venue": "園田",
        "venue_code": "50",
        "venue_type": "NAR",
        "race_no": 5,
        "レース名": "5R"
      }
    },
    {
      "race_id": "202650040206",
      "race_info": {
        "venue": "園田",
        "venue_code": "50",
        "venue_type": "NAR",
        "race_no": 6,
        "レース名": "6R"
      }
    },
    {
      "race_id": "202650040207",
      "race_info": {
        "venue": "園田",
        "venue_code": "50",
        "venue_type": "NAR",
        "race_no": 7,
        "レース名": "7R"
      }
    },
    {
      "race_id": "202650040208",
      "race_info": {
        "venue": "園田",
        "venue_code": "50",
        "venue_type": "NAR",
        "race_no": 8,
        "レース名": "8R"
      }
    },
    {
      "race_id": "202650040209",
      "race_info": {
        "venue": "園田",
        "venue_code": "50",
        "venue_type": "NAR",
        "race_no": 9,
        "レース名": "9R"
      }
    },
    {
      "race_id": "202650040210",
      "race_info": {
        "venue": "園田",
        "venue_code": "50",
        "venue_type": "NAR",
        "race_no": 10,
        "レース名": "10R"
      }
    },
    {
      "race_id": "202650040211",
      "race_info": {
        "venue": "園田",
        "venue_code": "50",
        "venue_type": "NAR",
        "race_no": 11,
        "レース名": "11R"
      }
    },
    {
      "race_id": "202650040212",
      "race_info": {
        "venue": "園田",
        "venue_code": "50",
        "venue_type": "NAR",
        "race_no": 12,
        "レース名": "12R"
      }
    }
  ],
  "races_by_venue": {
    "43": {
      "name": "船橋",
      "type": "NAR",
      "race_id_map": {
        "1": "202643040201",
        "2": "202643040202",
        "3": "202643040203",
        "4": "202643040204",
        "5": "202643040205",
        "6": "202643040206",
        "7": "202643040207",
        "8": "202643040208",
        "9": "202643040209",
        "10": "202643040210",
        "11": "202643040211",
        "12": "202643040212"
      }
    },
    "47": {
      "name": "笠松",
      "type": "NAR",
      "race_id_map": {
        "1": "202647040201",
        "2": "202647040202",
        "3": "202647040203",
        "4": "202647040204",
        "5": "202647040205",
        "6": "202647040206",
        "7": "202647040207",
        "8": "202647040208",
        "9": "202647040209",
        "10": "202647040210",
        "11": "202647040211"
      }
    },
    "50": {
      "name": "園田",
      "type": "NAR",
      "race_id_map": {
        "1": "202650040201",
        "2": "202650040202",
        "3": "202650040203",
        "4": "202650040204",
        "5": "202650040205",
        "6": "202650040206",
        "7": "202650040207",
        "8": "202650040208",
        "9": "202650040209",
        "10": "202650040210",
        "11": "202650040211",
        "12": "202650040212"
      }
    }
  }
}